worde4mde/__init__.py
worde4mde/load_embeddings.py
worde4mde-1.0.dist-info/LICENSE
worde4mde-1.0.dist-info/METADATA
worde4mde-1.0.dist-info/WHEEL
worde4mde-1.0.dist-info/top_level.txt
worde4mde-1.0.dist-info/RECORD
