Metadata-Version: 2.1
Name: worde4mde
Version: 1.0
Summary: Embeddings for software modeling
Home-page: https://github.com/models-lab/worde4mde
Author: Jesús Sánchez Cuadrado
Author-email: jesusc@um.es
Project-URL: Bug Tracker, https://github.com/models-lab/worde4mde/issues
Classifier: Programming Language :: Python :: 3
Classifier: License :: OSI Approved :: MIT License
Classifier: Operating System :: OS Independent
Requires-Python: >=3.0
License-File: LICENSE
Requires-Dist: gensim (==4.2.0)
Requires-Dist: gdown
